Gongge
