Metadata-Version: 2.1
Name: Gongge
Version: 0.0.7
Summary: 九宫格图片分割，最简单的Python图像分割工具。
Home-page: https://github.com/xuehang00126
Author: 学航
Author-email: 30290382@qq.com
License: MIT License
Keywords: img
Platform: any
